[
    {
        "step": 1,
        "cluster_i": 34,
        "cluster_j": 153,
        "dist": 0.0
    },
    {
        "step": 2,
        "cluster_i": 139,
        "cluster_j": 179,
        "dist": 0.0
    },
    {
        "step": 3,
        "cluster_i": 211,
        "cluster_j": 181,
        "dist": 0.0
    },
    {
        "step": 4,
        "cluster_i": 52,
        "cluster_j": 144,
        "dist": 0.0
    },
    {
        "step": 5,
        "cluster_i": 1,
        "cluster_j": 44,
        "dist": 0.0
    },
    {
        "step": 6,
        "cluster_i": 214,
        "cluster_j": 183,
        "dist": 0.0
    },
    {
        "step": 7,
        "cluster_i": 0,
        "cluster_j": 169,
        "dist": 0.0013855478970756507
    },
    {
        "step": 8,
        "cluster_i": 180,
        "cluster_j": 41,
        "dist": 0.0013855478970756507
    },
    {
        "step": 9,
        "cluster_i": 48,
        "cluster_j": 215,
        "dist": 0.002613822185477871
    },
    {
        "step": 10,
        "cluster_i": 166,
        "cluster_j": 35,
        "dist": 0.002692458989814586
    },
    {
        "step": 11,
        "cluster_i": 3,
        "cluster_j": 178,
        "dist": 0.002692458989814586
    },
    {
        "step": 12,
        "cluster_i": 185,
        "cluster_j": 170,
        "dist": 0.002692458989814586
    },
    {
        "step": 13,
        "cluster_i": 221,
        "cluster_j": 210,
        "dist": 0.002692458989814586
    },
    {
        "step": 14,
        "cluster_i": 69,
        "cluster_j": 186,
        "dist": 0.0027710957941513015
    },
    {
        "step": 15,
        "cluster_i": 32,
        "cluster_j": 61,
        "dist": 0.0027710957941513015
    },
    {
        "step": 16,
        "cluster_i": 222,
        "cluster_j": 16,
        "dist": 0.003920733278216806
    },
    {
        "step": 17,
        "cluster_i": 161,
        "cluster_j": 195,
        "dist": 0.003999370082553522
    },
    {
        "step": 18,
        "cluster_i": 220,
        "cluster_j": 57,
        "dist": 0.003999370082553522
    },
    {
        "step": 19,
        "cluster_i": 88,
        "cluster_j": 72,
        "dist": 0.003999370082553522
    },
    {
        "step": 20,
        "cluster_i": 226,
        "cluster_j": 172,
        "dist": 0.004078006886890237
    },
    {
        "step": 21,
        "cluster_i": 124,
        "cluster_j": 122,
        "dist": 0.004902157507937849
    },
    {
        "step": 22,
        "cluster_i": 142,
        "cluster_j": 229,
        "dist": 0.005384917979629172
    },
    {
        "step": 23,
        "cluster_i": 225,
        "cluster_j": 21,
        "dist": 0.005384917979629172
    },
    {
        "step": 24,
        "cluster_i": 227,
        "cluster_j": 76,
        "dist": 0.005463554783965888
    },
    {
        "step": 25,
        "cluster_i": 59,
        "cluster_j": 204,
        "dist": 0.005502227124446257
    },
    {
        "step": 26,
        "cluster_i": 212,
        "cluster_j": 234,
        "dist": 0.005502227124446368
    },
    {
        "step": 27,
        "cluster_i": 231,
        "cluster_j": 219,
        "dist": 0.006534555463694677
    },
    {
        "step": 28,
        "cluster_i": 85,
        "cluster_j": 236,
        "dist": 0.0068491026810415245
    },
    {
        "step": 29,
        "cluster_i": 54,
        "cluster_j": 94,
        "dist": 0.007060048636282137
    },
    {
        "step": 30,
        "cluster_i": 224,
        "cluster_j": 131,
        "dist": 0.007752109510220637
    },
    {
        "step": 31,
        "cluster_i": 228,
        "cluster_j": 39,
        "dist": 0.007998740165107043
    },
    {
        "step": 32,
        "cluster_i": 155,
        "cluster_j": 237,
        "dist": 0.008077376969443759
    },
    {
        "step": 33,
        "cluster_i": 163,
        "cluster_j": 50,
        "dist": 0.00823465057811719
    },
    {
        "step": 34,
        "cluster_i": 168,
        "cluster_j": 199,
        "dist": 0.008313287382453904
    },
    {
        "step": 35,
        "cluster_i": 238,
        "cluster_j": 71,
        "dist": 0.00925197891127881
    },
    {
        "step": 36,
        "cluster_i": 149,
        "cluster_j": 84,
        "dist": 0.009305651257845979
    },
    {
        "step": 37,
        "cluster_i": 230,
        "cluster_j": 152,
        "dist": 0.009384288062182694
    },
    {
        "step": 38,
        "cluster_i": 198,
        "cluster_j": 223,
        "dist": 0.00950159720699989
    },
    {
        "step": 39,
        "cluster_i": 31,
        "cluster_j": 75,
        "dist": 0.00962019847519284
    },
    {
        "step": 40,
        "cluster_i": 244,
        "cluster_j": 240,
        "dist": 0.00962019847519284
    },
    {
        "step": 41,
        "cluster_i": 242,
        "cluster_j": 249,
        "dist": 0.010067054843443585
    },
    {
        "step": 42,
        "cluster_i": 233,
        "cluster_j": 217,
        "dist": 0.010612562350584914
    },
    {
        "step": 43,
        "cluster_i": 232,
        "cluster_j": 190,
        "dist": 0.01088714510407554
    },
    {
        "step": 44,
        "cluster_i": 148,
        "cluster_j": 248,
        "dist": 0.01100574637226849
    },
    {
        "step": 45,
        "cluster_i": 252,
        "cluster_j": 128,
        "dist": 0.01120121139501866
    },
    {
        "step": 46,
        "cluster_i": 77,
        "cluster_j": 246,
        "dist": 0.01125088063266283
    },
    {
        "step": 47,
        "cluster_i": 151,
        "cluster_j": 141,
        "dist": 0.011498758805540757
    },
    {
        "step": 48,
        "cluster_i": 254,
        "cluster_j": 135,
        "dist": 0.012351329805487796
    },
    {
        "step": 49,
        "cluster_i": 216,
        "cluster_j": 241,
        "dist": 0.013069110927389355
    },
    {
        "step": 50,
        "cluster_i": 247,
        "cluster_j": 251,
        "dist": 0.013776842166419764
    },
    {
        "step": 51,
        "cluster_i": 259,
        "cluster_j": 257,
        "dist": 0.013776842166419792
    },
    {
        "step": 52,
        "cluster_i": 99,
        "cluster_j": 10,
        "dist": 0.014611932433138436
    },
    {
        "step": 53,
        "cluster_i": 46,
        "cluster_j": 256,
        "dist": 0.014661264736537442
    },
    {
        "step": 54,
        "cluster_i": 255,
        "cluster_j": 145,
        "dist": 0.016127020415123483
    },
    {
        "step": 55,
        "cluster_i": 73,
        "cluster_j": 114,
        "dist": 0.016429336692378005
    },
    {
        "step": 56,
        "cluster_i": 258,
        "cluster_j": 260,
        "dist": 0.016469301156234392
    },
    {
        "step": 57,
        "cluster_i": 177,
        "cluster_j": 70,
        "dist": 0.016547937960571094
    },
    {
        "step": 58,
        "cluster_i": 265,
        "cluster_j": 147,
        "dist": 0.016815428442792296
    },
    {
        "step": 59,
        "cluster_i": 92,
        "cluster_j": 263,
        "dist": 0.017255203111712594
    },
    {
        "step": 60,
        "cluster_i": 103,
        "cluster_j": 26,
        "dist": 0.01749325132192206
    },
    {
        "step": 61,
        "cluster_i": 66,
        "cluster_j": 159,
        "dist": 0.017948286312810507
    },
    {
        "step": 62,
        "cluster_i": 239,
        "cluster_j": 49,
        "dist": 0.018286035056468822
    },
    {
        "step": 63,
        "cluster_i": 271,
        "cluster_j": 29,
        "dist": 0.01900448653737552
    },
    {
        "step": 64,
        "cluster_i": 267,
        "cluster_j": 209,
        "dist": 0.019120503558816865
    },
    {
        "step": 65,
        "cluster_i": 208,
        "cluster_j": 82,
        "dist": 0.01920043248652944
    },
    {
        "step": 66,
        "cluster_i": 202,
        "cluster_j": 123,
        "dist": 0.019357706095202876
    },
    {
        "step": 67,
        "cluster_i": 269,
        "cluster_j": 262,
        "dist": 0.019544284204814008
    },
    {
        "step": 68,
        "cluster_i": 86,
        "cluster_j": 132,
        "dist": 0.021932855940200238
    },
    {
        "step": 69,
        "cluster_i": 268,
        "cluster_j": 14,
        "dist": 0.022048872961641486
    },
    {
        "step": 70,
        "cluster_i": 90,
        "cluster_j": 278,
        "dist": 0.02214681875441385
    },
    {
        "step": 71,
        "cluster_i": 60,
        "cluster_j": 15,
        "dist": 0.02431076771266799
    },
    {
        "step": 72,
        "cluster_i": 55,
        "cluster_j": 206,
        "dist": 0.024604378322115456
    },
    {
        "step": 73,
        "cluster_i": 58,
        "cluster_j": 192,
        "dist": 0.02474262407483191
    },
    {
        "step": 74,
        "cluster_i": 279,
        "cluster_j": 22,
        "dist": 0.024760640939891693
    },
    {
        "step": 75,
        "cluster_i": 140,
        "cluster_j": 64,
        "dist": 0.02624677324010065
    },
    {
        "step": 76,
        "cluster_i": 51,
        "cluster_j": 53,
        "dist": 0.02690971017374655
    },
    {
        "step": 77,
        "cluster_i": 273,
        "cluster_j": 138,
        "dist": 0.02855808692585618
    },
    {
        "step": 78,
        "cluster_i": 250,
        "cluster_j": 272,
        "dist": 0.028624685012568346
    },
    {
        "step": 79,
        "cluster_i": 119,
        "cluster_j": 102,
        "dist": 0.0287770145148885
    },
    {
        "step": 80,
        "cluster_i": 276,
        "cluster_j": 288,
        "dist": 0.03003776352574352
    },
    {
        "step": 81,
        "cluster_i": 264,
        "cluster_j": 175,
        "dist": 0.030167506518317455
    },
    {
        "step": 82,
        "cluster_i": 121,
        "cluster_j": 107,
        "dist": 0.03196585941692261
    },
    {
        "step": 83,
        "cluster_i": 253,
        "cluster_j": 283,
        "dist": 0.03234940237626771
    },
    {
        "step": 84,
        "cluster_i": 287,
        "cluster_j": 270,
        "dist": 0.033852329383524116
    },
    {
        "step": 85,
        "cluster_i": 280,
        "cluster_j": 203,
        "dist": 0.035119276012406817
    },
    {
        "step": 86,
        "cluster_i": 293,
        "cluster_j": 7,
        "dist": 0.0374061231607276
    },
    {
        "step": 87,
        "cluster_i": 187,
        "cluster_j": 235,
        "dist": 0.03740979322104257
    },
    {
        "step": 88,
        "cluster_i": 292,
        "cluster_j": 78,
        "dist": 0.037782709355081726
    },
    {
        "step": 89,
        "cluster_i": 297,
        "cluster_j": 167,
        "dist": 0.03808552405490702
    },
    {
        "step": 90,
        "cluster_i": 286,
        "cluster_j": 289,
        "dist": 0.03848787995095623
    },
    {
        "step": 91,
        "cluster_i": 43,
        "cluster_j": 111,
        "dist": 0.03931588416748999
    },
    {
        "step": 92,
        "cluster_i": 165,
        "cluster_j": 125,
        "dist": 0.03970648394242174
    },
    {
        "step": 93,
        "cluster_i": 298,
        "cluster_j": 294,
        "dist": 0.03990501413832749
    },
    {
        "step": 94,
        "cluster_i": 299,
        "cluster_j": 290,
        "dist": 0.040414645544248715
    },
    {
        "step": 95,
        "cluster_i": 11,
        "cluster_j": 30,
        "dist": 0.04216561676597802
    },
    {
        "step": 96,
        "cluster_i": 129,
        "cluster_j": 38,
        "dist": 0.042633561221870606
    },
    {
        "step": 97,
        "cluster_i": 109,
        "cluster_j": 164,
        "dist": 0.043185741338400044
    },
    {
        "step": 98,
        "cluster_i": 303,
        "cluster_j": 305,
        "dist": 0.043381687287553816
    },
    {
        "step": 99,
        "cluster_i": 307,
        "cluster_j": 282,
        "dist": 0.044414015626802264
    },
    {
        "step": 100,
        "cluster_i": 20,
        "cluster_j": 284,
        "dist": 0.044807199648485854
    },
    {
        "step": 101,
        "cluster_i": 18,
        "cluster_j": 101,
        "dist": 0.045302163058048864
    },
    {
        "step": 102,
        "cluster_i": 158,
        "cluster_j": 266,
        "dist": 0.04595683713255132
    },
    {
        "step": 103,
        "cluster_i": 197,
        "cluster_j": 23,
        "dist": 0.04648788863584301
    },
    {
        "step": 104,
        "cluster_i": 13,
        "cluster_j": 12,
        "dist": 0.04737776641466868
    },
    {
        "step": 105,
        "cluster_i": 308,
        "cluster_j": 313,
        "dist": 0.0479285749601112
    },
    {
        "step": 106,
        "cluster_i": 309,
        "cluster_j": 306,
        "dist": 0.048100992375964186
    },
    {
        "step": 107,
        "cluster_i": 100,
        "cluster_j": 243,
        "dist": 0.04892387887585657
    },
    {
        "step": 108,
        "cluster_i": 8,
        "cluster_j": 67,
        "dist": 0.048957042034514675
    },
    {
        "step": 109,
        "cluster_i": 302,
        "cluster_j": 207,
        "dist": 0.0490353049570767
    },
    {
        "step": 110,
        "cluster_i": 301,
        "cluster_j": 157,
        "dist": 0.04964252175833729
    },
    {
        "step": 111,
        "cluster_i": 295,
        "cluster_j": 42,
        "dist": 0.052491392596245995
    },
    {
        "step": 112,
        "cluster_i": 314,
        "cluster_j": 91,
        "dist": 0.05312752230426257
    },
    {
        "step": 113,
        "cluster_i": 319,
        "cluster_j": 150,
        "dist": 0.05419019558729278
    },
    {
        "step": 114,
        "cluster_i": 116,
        "cluster_j": 146,
        "dist": 0.055124047908540086
    },
    {
        "step": 115,
        "cluster_i": 113,
        "cluster_j": 318,
        "dist": 0.05527977508360925
    },
    {
        "step": 116,
        "cluster_i": 315,
        "cluster_j": 106,
        "dist": 0.055419761999070755
    },
    {
        "step": 117,
        "cluster_i": 4,
        "cluster_j": 171,
        "dist": 0.05814931283305472
    },
    {
        "step": 118,
        "cluster_i": 291,
        "cluster_j": 205,
        "dist": 0.058522056216607735
    },
    {
        "step": 119,
        "cluster_i": 324,
        "cluster_j": 312,
        "dist": 0.061910046265985036
    },
    {
        "step": 120,
        "cluster_i": 74,
        "cluster_j": 176,
        "dist": 0.06501782378293104
    },
    {
        "step": 121,
        "cluster_i": 322,
        "cluster_j": 47,
        "dist": 0.06539318003209083
    },
    {
        "step": 122,
        "cluster_i": 321,
        "cluster_j": 275,
        "dist": 0.06845600645291243
    },
    {
        "step": 123,
        "cluster_i": 320,
        "cluster_j": 27,
        "dist": 0.06974706179584753
    },
    {
        "step": 124,
        "cluster_i": 327,
        "cluster_j": 2,
        "dist": 0.06978446386733742
    },
    {
        "step": 125,
        "cluster_i": 333,
        "cluster_j": 118,
        "dist": 0.0701116717830215
    },
    {
        "step": 126,
        "cluster_i": 104,
        "cluster_j": 316,
        "dist": 0.0702697587291746
    },
    {
        "step": 127,
        "cluster_i": 328,
        "cluster_j": 323,
        "dist": 0.0740726024024283
    },
    {
        "step": 128,
        "cluster_i": 136,
        "cluster_j": 311,
        "dist": 0.07588843323785865
    },
    {
        "step": 129,
        "cluster_i": 331,
        "cluster_j": 330,
        "dist": 0.07699896801864722
    },
    {
        "step": 130,
        "cluster_i": 335,
        "cluster_j": 33,
        "dist": 0.07750859942456856
    },
    {
        "step": 131,
        "cluster_i": 310,
        "cluster_j": 36,
        "dist": 0.07777363244028691
    },
    {
        "step": 132,
        "cluster_i": 337,
        "cluster_j": 156,
        "dist": 0.08279309992199654
    },
    {
        "step": 133,
        "cluster_i": 19,
        "cluster_j": 95,
        "dist": 0.085783214466542
    },
    {
        "step": 134,
        "cluster_i": 325,
        "cluster_j": 341,
        "dist": 0.08744248335652888
    },
    {
        "step": 135,
        "cluster_i": 338,
        "cluster_j": 317,
        "dist": 0.08855304080993232
    },
    {
        "step": 136,
        "cluster_i": 201,
        "cluster_j": 184,
        "dist": 0.08898616662285731
    },
    {
        "step": 137,
        "cluster_i": 343,
        "cluster_j": 97,
        "dist": 0.0896674292882337
    },
    {
        "step": 138,
        "cluster_i": 126,
        "cluster_j": 329,
        "dist": 0.090230114799828
    },
    {
        "step": 139,
        "cluster_i": 5,
        "cluster_j": 40,
        "dist": 0.09589212543037112
    },
    {
        "step": 140,
        "cluster_i": 196,
        "cluster_j": 326,
        "dist": 0.0959394001667551
    },
    {
        "step": 141,
        "cluster_i": 130,
        "cluster_j": 37,
        "dist": 0.09847350070310393
    },
    {
        "step": 142,
        "cluster_i": 336,
        "cluster_j": 133,
        "dist": 0.10181480337028125
    },
    {
        "step": 143,
        "cluster_i": 344,
        "cluster_j": 334,
        "dist": 0.10482981935172914
    },
    {
        "step": 144,
        "cluster_i": 339,
        "cluster_j": 285,
        "dist": 0.10512259483001433
    },
    {
        "step": 145,
        "cluster_i": 352,
        "cluster_j": 353,
        "dist": 0.1069982892848407
    },
    {
        "step": 146,
        "cluster_i": 354,
        "cluster_j": 24,
        "dist": 0.1163749142812459
    },
    {
        "step": 147,
        "cluster_i": 332,
        "cluster_j": 17,
        "dist": 0.11853055872564655
    },
    {
        "step": 148,
        "cluster_i": 342,
        "cluster_j": 350,
        "dist": 0.1207893945780138
    },
    {
        "step": 149,
        "cluster_i": 351,
        "cluster_j": 137,
        "dist": 0.12535358786363004
    },
    {
        "step": 150,
        "cluster_i": 355,
        "cluster_j": 110,
        "dist": 0.13033466685135872
    },
    {
        "step": 151,
        "cluster_i": 349,
        "cluster_j": 357,
        "dist": 0.1308461077205252
    },
    {
        "step": 152,
        "cluster_i": 347,
        "cluster_j": 173,
        "dist": 0.13106417035241735
    },
    {
        "step": 153,
        "cluster_i": 108,
        "cluster_j": 358,
        "dist": 0.13296681118019055
    },
    {
        "step": 154,
        "cluster_i": 360,
        "cluster_j": 193,
        "dist": 0.13326257804393182
    },
    {
        "step": 155,
        "cluster_i": 359,
        "cluster_j": 89,
        "dist": 0.13749129014414097
    },
    {
        "step": 156,
        "cluster_i": 112,
        "cluster_j": 361,
        "dist": 0.14226265781170955
    },
    {
        "step": 157,
        "cluster_i": 6,
        "cluster_j": 9,
        "dist": 0.1487181308713966
    },
    {
        "step": 158,
        "cluster_i": 174,
        "cluster_j": 340,
        "dist": 0.1511967908398763
    },
    {
        "step": 159,
        "cluster_i": 364,
        "cluster_j": 28,
        "dist": 0.15334985920319108
    },
    {
        "step": 160,
        "cluster_i": 346,
        "cluster_j": 348,
        "dist": 0.15619718127698434
    },
    {
        "step": 161,
        "cluster_i": 365,
        "cluster_j": 274,
        "dist": 0.16341601505059
    },
    {
        "step": 162,
        "cluster_i": 356,
        "cluster_j": 83,
        "dist": 0.1636034670656919
    },
    {
        "step": 163,
        "cluster_i": 371,
        "cluster_j": 81,
        "dist": 0.167515797725657
    },
    {
        "step": 164,
        "cluster_i": 370,
        "cluster_j": 182,
        "dist": 0.18984473832030957
    },
    {
        "step": 165,
        "cluster_i": 218,
        "cluster_j": 143,
        "dist": 0.2189634735961916
    },
    {
        "step": 166,
        "cluster_i": 368,
        "cluster_j": 281,
        "dist": 0.2345411720503084
    },
    {
        "step": 167,
        "cluster_i": 372,
        "cluster_j": 304,
        "dist": 0.2382038705465773
    },
    {
        "step": 168,
        "cluster_i": 376,
        "cluster_j": 45,
        "dist": 0.23944907532591364
    },
    {
        "step": 169,
        "cluster_i": 369,
        "cluster_j": 62,
        "dist": 0.2570297844301152
    },
    {
        "step": 170,
        "cluster_i": 374,
        "cluster_j": 160,
        "dist": 0.27460902407696874
    },
    {
        "step": 171,
        "cluster_i": 377,
        "cluster_j": 261,
        "dist": 0.33675849777674133
    },
    {
        "step": 172,
        "cluster_i": 378,
        "cluster_j": 277,
        "dist": 0.402871612814689
    },
    {
        "step": 173,
        "cluster_i": 25,
        "cluster_j": 367,
        "dist": 0.43171972845113304
    },
    {
        "step": 174,
        "cluster_i": 363,
        "cluster_j": 362,
        "dist": 0.45644833965669074
    },
    {
        "step": 175,
        "cluster_i": 296,
        "cluster_j": 213,
        "dist": 0.8795161266113622
    },
    {
        "step": 176,
        "cluster_i": 383,
        "cluster_j": 115,
        "dist": 0.8820124530883965
    },
    {
        "step": 177,
        "cluster_i": 381,
        "cluster_j": 380,
        "dist": 0.8822085856011769
    },
    {
        "step": 178,
        "cluster_i": 375,
        "cluster_j": 68,
        "dist": 0.9053284592425471
    },
    {
        "step": 179,
        "cluster_i": 373,
        "cluster_j": 194,
        "dist": 0.9262302789668749
    },
    {
        "step": 180,
        "cluster_i": 154,
        "cluster_j": 98,
        "dist": 0.9973880433396125
    },
    {
        "step": 181,
        "cluster_i": 387,
        "cluster_j": 79,
        "dist": 1.1124135912657587
    },
    {
        "step": 182,
        "cluster_i": 300,
        "cluster_j": 382,
        "dist": 1.121377826956365
    },
    {
        "step": 183,
        "cluster_i": 134,
        "cluster_j": 65,
        "dist": 1.133583653430899
    },
    {
        "step": 184,
        "cluster_i": 386,
        "cluster_j": 389,
        "dist": 1.1501089094703
    },
    {
        "step": 185,
        "cluster_i": 390,
        "cluster_j": 385,
        "dist": 1.1756264457927108
    },
    {
        "step": 186,
        "cluster_i": 393,
        "cluster_j": 87,
        "dist": 1.2253919765207342
    },
    {
        "step": 187,
        "cluster_i": 394,
        "cluster_j": 388,
        "dist": 1.474358989188341
    },
    {
        "step": 188,
        "cluster_i": 96,
        "cluster_j": 56,
        "dist": 1.4981492138516375
    },
    {
        "step": 189,
        "cluster_i": 396,
        "cluster_j": 345,
        "dist": 1.5555810566083406
    },
    {
        "step": 190,
        "cluster_i": 395,
        "cluster_j": 392,
        "dist": 1.5683282815247312
    },
    {
        "step": 191,
        "cluster_i": 379,
        "cluster_j": 188,
        "dist": 1.5797236390688847
    },
    {
        "step": 192,
        "cluster_i": 398,
        "cluster_j": 189,
        "dist": 1.5973755021326046
    },
    {
        "step": 193,
        "cluster_i": 401,
        "cluster_j": 117,
        "dist": 1.6340151836812606
    },
    {
        "step": 194,
        "cluster_i": 399,
        "cluster_j": 93,
        "dist": 1.7349440254041868
    },
    {
        "step": 195,
        "cluster_i": 402,
        "cluster_j": 403,
        "dist": 2.1168945503337895
    },
    {
        "step": 196,
        "cluster_i": 397,
        "cluster_j": 384,
        "dist": 2.1885807765602654
    },
    {
        "step": 197,
        "cluster_i": 400,
        "cluster_j": 191,
        "dist": 2.466033755635673
    },
    {
        "step": 198,
        "cluster_i": 404,
        "cluster_j": 80,
        "dist": 2.575676679647474
    },
    {
        "step": 199,
        "cluster_i": 391,
        "cluster_j": 366,
        "dist": 3.1976332585044602
    },
    {
        "step": 200,
        "cluster_i": 245,
        "cluster_j": 63,
        "dist": 3.738230980006192
    },
    {
        "step": 201,
        "cluster_i": 407,
        "cluster_j": 408,
        "dist": 4.3427755596578015
    },
    {
        "step": 202,
        "cluster_i": 410,
        "cluster_j": 405,
        "dist": 4.405638873145584
    },
    {
        "step": 203,
        "cluster_i": 411,
        "cluster_j": 409,
        "dist": 4.716900061119987
    },
    {
        "step": 204,
        "cluster_i": 412,
        "cluster_j": 200,
        "dist": 4.938937871840733
    },
    {
        "step": 205,
        "cluster_i": 413,
        "cluster_j": 406,
        "dist": 5.023141746345001
    },
    {
        "step": 206,
        "cluster_i": 120,
        "cluster_j": 127,
        "dist": 7.42454588674808
    },
    {
        "step": 207,
        "cluster_i": 414,
        "cluster_j": 415,
        "dist": 9.713506199804364
    },
    {
        "step": 208,
        "cluster_i": 416,
        "cluster_j": 105,
        "dist": 11.121004240556973
    },
    {
        "step": 209,
        "cluster_i": 417,
        "cluster_j": 162,
        "dist": 14.600949139649641
    }
]